dapperdata/__init__.py
dapperdata/_version.py
dapperdata/cli.py
dapperdata/settings.py
dapperdata/conf/__init__.py
dapperdata/conf/settings.py
dapperdata/formatters/__init__.py
dapperdata/formatters/json.py
dapperdata/formatters/yaml.py
tests/__init__.py
tests/test_json.py
tests/test_settings.py
tests/test_yaml.py
dapperdata-0.4.0.dist-info/LICENSE
dapperdata-0.4.0.dist-info/METADATA
dapperdata-0.4.0.dist-info/WHEEL
dapperdata-0.4.0.dist-info/entry_points.txt
dapperdata-0.4.0.dist-info/top_level.txt
dapperdata-0.4.0.dist-info/RECORD
