Metadata-Version: 2.1
Name: dapperdata
Version: 0.4.0
Summary: An opinionated formatter for configuration files.
License: MIT
Provides-Extra: dev
License-File: LICENSE
